charformer_pytorch/__init__.py
charformer_pytorch/charformer_pytorch.py
charformer_pytorch-0.0.4.dist-info/LICENSE
charformer_pytorch-0.0.4.dist-info/METADATA
charformer_pytorch-0.0.4.dist-info/WHEEL
charformer_pytorch-0.0.4.dist-info/top_level.txt
charformer_pytorch-0.0.4.dist-info/RECORD
