Metadata-Version: 2.1
Name: charformer-pytorch
Version: 0.0.4
Summary: Charformer - Pytorch
Home-page: https://github.com/lucidrains/charformer-pytorch
Author: Phil Wang
Author-email: lucidrains@gmail.com
License: MIT
Keywords: artificial intelligence,deep learning,learned tokenization
Platform: UNKNOWN
Classifier: Development Status :: 4 - Beta
Classifier: Intended Audience :: Developers
Classifier: Topic :: Scientific/Engineering :: Artificial Intelligence
Classifier: License :: OSI Approved :: MIT License
Classifier: Programming Language :: Python :: 3.6
License-File: LICENSE
Requires-Dist: einops (>=0.3)
Requires-Dist: torch (>=1.6)
